gdcm.py
_gdcm/__init__.py
_gdcm/_gdcmswig.so
_gdcm/gdcm.py
_gdcm/gdcmanon
_gdcm/gdcmclean
_gdcm/gdcmconv
_gdcm/gdcmdiff
_gdcm/gdcmdump
_gdcm/gdcmgendir
_gdcm/gdcmimg
_gdcm/gdcminfo
_gdcm/gdcmpap3
_gdcm/gdcmraw
_gdcm/gdcmscanner
_gdcm/gdcmscu
_gdcm/gdcmswig.py
_gdcm/gdcmtar
_gdcm/gdcmxml
_gdcm/libgdcmCommon.so
_gdcm/libgdcmCommon.so.3.2
_gdcm/libgdcmCommon.so.3.2.1
_gdcm/libgdcmDICT.so
_gdcm/libgdcmDICT.so.3.2
_gdcm/libgdcmDICT.so.3.2.1
_gdcm/libgdcmDSED.so
_gdcm/libgdcmDSED.so.3.2
_gdcm/libgdcmDSED.so.3.2.1
_gdcm/libgdcmIOD.so
_gdcm/libgdcmIOD.so.3.2
_gdcm/libgdcmIOD.so.3.2.1
_gdcm/libgdcmMEXD.so
_gdcm/libgdcmMEXD.so.3.2
_gdcm/libgdcmMEXD.so.3.2.1
_gdcm/libgdcmMSFF.so
_gdcm/libgdcmMSFF.so.3.2
_gdcm/libgdcmMSFF.so.3.2.1
_gdcm/libgdcmcharls.so
_gdcm/libgdcmcharls.so.2
_gdcm/libgdcmcharls.so.2.0
_gdcm/libgdcmexpat.so
_gdcm/libgdcmexpat.so.2.0
_gdcm/libgdcmexpat.so.2.0.0
_gdcm/libgdcmjpeg12.so
_gdcm/libgdcmjpeg12.so.3.2
_gdcm/libgdcmjpeg12.so.3.2.1
_gdcm/libgdcmjpeg16.so
_gdcm/libgdcmjpeg16.so.3.2
_gdcm/libgdcmjpeg16.so.3.2.1
_gdcm/libgdcmjpeg8.so
_gdcm/libgdcmjpeg8.so.3.2
_gdcm/libgdcmjpeg8.so.3.2.1
_gdcm/libgdcmopenjp2.so
_gdcm/libgdcmopenjp2.so.2.3.0
_gdcm/libgdcmopenjp2.so.7
_gdcm/libgdcmuuid.so
_gdcm/libgdcmuuid.so.3.2
_gdcm/libgdcmuuid.so.3.2.1
_gdcm/libgdcmzlib.so
_gdcm/libgdcmzlib.so.3.2
_gdcm/libgdcmzlib.so.3.2.1
_gdcm/libsocketxx.so
_gdcm/libsocketxx.so.1.2
_gdcm/libsocketxx.so.1.2.0
_gdcm/XML/CSAHeader.xml
_gdcm/XML/Part3.xml
_gdcm/XML/Part4.xml
_gdcm/XML/Part6.xml
_gdcm/XML/Part7a.xml
_gdcm/XML/Part7b.xml
_gdcm/XML/UIDs.xml
_gdcm/XML/cp699.xml
_gdcm/gdcmopenjpeg-2.3/OpenJPEGConfig.cmake
_gdcm/pkgconfig/libopenjp2.pc
_gdcm/scripts/gdcmanon.py
_gdcm/scripts/gdcmconv.py
_gdcm/scripts/gdcmdiff.py
_gdcm/scripts/gdcmdump.py
_gdcm/scripts/gdcmgendir.py
_gdcm/scripts/gdcmimg.py
_gdcm/scripts/gdcminfo.py
_gdcm/scripts/gdcmpap3.py
_gdcm/scripts/gdcmraw.py
_gdcm/scripts/gdcmscanner.py
python_gdcm-3.2.1.dist-info/METADATA
python_gdcm-3.2.1.dist-info/WHEEL
python_gdcm-3.2.1.dist-info/entry_points.txt
python_gdcm-3.2.1.dist-info/RECORD
python_gdcm-3.2.1.dist-info/licenses/LICENSE
